{"assets/fonts/Actor/Actor-Regular.ttf":["assets/fonts/Actor/Actor-Regular.ttf"],"assets/fonts/Lato/Lato-Bold.ttf":["assets/fonts/Lato/Lato-Bold.ttf"],"assets/fonts/Lato/Lato-Regular.ttf":["assets/fonts/Lato/Lato-Regular.ttf"],"assets/fonts/PretendardVariable/PretendardVariable.ttf":["assets/fonts/PretendardVariable/PretendardVariable.ttf"],"assets/fonts/Roboto/Roboto-Thin.ttf":["assets/fonts/Roboto/Roboto-Thin.ttf"],"assets/images/about_us_image.png":["assets/images/about_us_image.png"],"assets/images/chkmark.png":["assets/images/chkmark.png"],"assets/images/feature1.png":["assets/images/feature1.png"],"assets/images/feature2.png":["assets/images/feature2.png"],"assets/images/feature3.png":["assets/images/feature3.png"],"assets/images/logo.png":["assets/images/logo.png"],"assets/images/our_story_image.png":["assets/images/our_story_image.png"],"assets/images/platform1.png":["assets/images/platform1.png"],"assets/images/platform2.png":["assets/images/platform2.png"],"assets/images/products_image.png":["assets/images/products_image.png"],"assets/images/sono_icon.png":["assets/images/sono_icon.png"],"assets/images/support1.png":["assets/images/support1.png"],"assets/images/support2.png":["assets/images/support2.png"],"assets/images/support3.png":["assets/images/support3.png"],"assets/images/value1.png":["assets/images/value1.png"],"assets/images/value2.png":["assets/images/value2.png"],"assets/images/value3.png":["assets/images/value3.png"],"packages/cupertino_icons/assets/CupertinoIcons.ttf":["packages/cupertino_icons/assets/CupertinoIcons.ttf"]}